src/__init__.py
src/pattern_gen.py
sim_generator-1.3.8.dist-info/LICENSE.txt
sim_generator-1.3.8.dist-info/METADATA
sim_generator-1.3.8.dist-info/WHEEL
sim_generator-1.3.8.dist-info/top_level.txt
sim_generator-1.3.8.dist-info/RECORD
